gps_frames/__init__.py
gps_frames/basis.py
gps_frames/parameters.py
gps_frames/paths.py
gps_frames/position.py
gps_frames/rotations.py
gps_frames/transforms.py
gps_frames/vectors.py
gps_frames/velocity.py
gps_frames/data/__init__.py
gps_frames/data/geoid_data_1deg.npz
gps_frames-3.0.0.dist-info/licenses/LICENSE
gps_frames-3.0.0.dist-info/METADATA
gps_frames-3.0.0.dist-info/WHEEL
gps_frames-3.0.0.dist-info/top_level.txt
gps_frames-3.0.0.dist-info/RECORD
