Metadata-Version: 2.4
Name: gps_frames
Version: 3.0.0
Summary: Reference frames representations and transformations
Author-email: David William Allen <david.w.allen@aero.org>
License: GNU AGPL v3
Project-URL: Repository, https://github.com/the-aerospace-corporation/gps_frames
Classifier: Development Status :: 4 - Beta
Classifier: Programming Language :: Python :: 3.7
Classifier: Programming Language :: Python :: 3.8
Classifier: Programming Language :: Python :: 3.9
Classifier: Programming Language :: Python :: 3.10
Classifier: Programming Language :: Python :: 3.11
Classifier: Programming Language :: Python :: 3.12
Classifier: Programming Language :: Python :: 3.13
Requires-Python: >=3.7
License-File: LICENSE
Requires-Dist: gps-time
Requires-Dist: numpy
Requires-Dist: numba
Requires-Dist: scipy
Provides-Extra: test
Requires-Dist: pytest; extra == "test"
Requires-Dist: pytest-cov; extra == "test"
Requires-Dist: setuptools; extra == "test"
Requires-Dist: genbadge[coverage]; extra == "test"
Provides-Extra: docs
Requires-Dist: mkdocs; extra == "docs"
Requires-Dist: mkdocs-material; extra == "docs"
Requires-Dist: mkdocstrings[python]; extra == "docs"
Requires-Dist: pymdown-extensions; extra == "docs"
Requires-Dist: mike; extra == "docs"
Provides-Extra: examples
Requires-Dist: matplotlib; extra == "examples"
Dynamic: license-file
